amersham/__init__.py
amersham/command.py
amersham/flag.py
amersham/parameter.py
amersham/parse_exception.py
amersham/parser.py
amersham/table.py
amersham/type.py
amersham-1.0.1.dist-info/LICENSE
amersham-1.0.1.dist-info/METADATA
amersham-1.0.1.dist-info/WHEEL
amersham-1.0.1.dist-info/top_level.txt
amersham-1.0.1.dist-info/RECORD
