Metadata-Version: 2.1
Name: amersham
Version: 1.0.1
Summary: A lightweight verbose argument parser
Home-page: https://github.com/inigo-selwood/amersham
Author: Inigo Selwood
Author-email: inigo.selwood@outlook.com
Project-URL: Bug Tracker, https://github.com/inigo-selwood/amersham
Classifier: Programming Language :: Python :: 3
Classifier: License :: OSI Approved :: MIT License
Classifier: Operating System :: OS Independent
Requires-Python: >=3.6
License-File: LICENSE
